README.md
setup.py
avilabs_torchutils.egg-info/PKG-INFO
avilabs_torchutils.egg-info/SOURCES.txt
avilabs_torchutils.egg-info/dependency_links.txt
avilabs_torchutils.egg-info/requires.txt
avilabs_torchutils.egg-info/top_level.txt
torchutils/__init__.py
torchutils/evaluator.py
torchutils/hyperparams.py
torchutils/ml_logger.py
torchutils/trainer.py
torchutils/tuner.py
torchutils/examples/__init__.py
torchutils/examples/binary_classification_mlflow.py
torchutils/examples/multiclass_classification_full.py
torchutils/examples/regression_stdout.py
torchutils/ml_loggers/__init__.py
torchutils/ml_loggers/csv_logger.py
torchutils/ml_loggers/mlflow_logger.py
torchutils/ml_loggers/stdout_logger.py
torchutils/visualizers/__init__.py
torchutils/visualizers/csv_metrics_visualizer.py