Metadata-Version: 1.0
Name: avilabs-torchutils
Version: 3.0.1
Summary: Convenience utils for using pytorch
Home-page: https://gitlab.com/avilay/torchutils
Author: Avilay Parekh
Author-email: avilay@gmail.com
License: MIT
Platform: UNKNOWN
